pyMSA-0.5.1.dist-info/METADATA
pyMSA-0.5.1.dist-info/RECORD
pyMSA-0.5.1.dist-info/WHEEL
pyMSA-0.5.1.dist-info/top_level.txt
pymsa/__init__.py
pymsa/core/__init__.py
pymsa/core/score.py
pymsa/core/substitution_matrix.py
pymsa/tests/__init__.py
pymsa/tests/test_score.py
pymsa/tests/test_substitution_matrix.py
pymsa/util/__init__.py
pymsa/util/fasta.py
pymsa/util/tool.py
