Metadata-Version: 2.1
Name: pyMSA
Version: 0.5.1
Summary: Scoring Multiple Sequence Alignments with Python
Home-page: https://github.com/benhid/pyMSA
Author: Antonio Benítez-Hidalgo, Antonio J. Nebro
Author-email: antonio.b@uma.es
Maintainer: Antonio Benítez-Hidalgo
Maintainer-email: antonio.b@uma.es
License: MIT
Platform: UNKNOWN
Classifier: Development Status :: 3 - Alpha
Classifier: Intended Audience :: Science/Research
Classifier: License :: OSI Approved :: MIT License
Classifier: Topic :: Scientific/Engineering :: Artificial Intelligence
Classifier: Programming Language :: Python :: 3.6
Requires-Python: >=3
